{
  "backtestConfig": {
    "endDate": "2026-01-21",
    "initialCapital": 100000000,
    "portfolio": {
      "maxPositions": 5,
      "minPositionPercent": 5,
      "positionSizePercent": 20
    },
    "riskManagement": {
      "maxHoldingDays": 21,
      "stopLoss": {
        "method": "FIXED",
        "percent": 7
      },
      "takeProfit": {
        "method": "FIXED",
        "percent": 18
      }
    },
    "startDate": "2022-03-14",
    "tradingCosts": {
      "brokerFee": 0.15,
      "minimumFee": 1000,
      "sellFee": 0.15,
      "slippageBps": 5.0,
      "spreadBps": 10.0
    }
  },
  "backtestId": "sma_trend_value_pe_shortPeriod20_longPeriod50_max12",
  "filters": {
    "marketCap": [
      "large",
      "mid"
    ]
  },
  "fundamentalIndicators": [
    {
      "max": 12,
      "type": "PE_RATIO"
    }
  ],
  "technicalIndicators": [
    {
      "longPeriod": 50,
      "shortPeriod": 20,
      "type": "SMA_TREND"
    }
  ]
}